musicfp/__init__.py
musicfp/__main__.py
musicfp-0.0.2.dist-info/LICENSE
musicfp-0.0.2.dist-info/METADATA
musicfp-0.0.2.dist-info/WHEEL
musicfp-0.0.2.dist-info/entry_points.txt
musicfp-0.0.2.dist-info/top_level.txt
musicfp-0.0.2.dist-info/RECORD
