Metadata-Version: 2.1
Name: musicfp
Version: 0.0.2
Summary: A terminal based media player for programmers
Home-page: https://github.com/SatvikVirmani/musicfp
Author: Satvik Virmani
Author-email: virmanisatvik01@gmail.com
License: UNKNOWN
Project-URL: Bug Tracker, https://github.com/SatvikVirmani/musicfp/issues
Platform: UNKNOWN
Classifier: Programming Language :: Python :: 3
Classifier: Development Status :: 5 - Production/Stable
Classifier: License :: OSI Approved :: MIT License
Classifier: Operating System :: OS Independent
Classifier: Topic :: Multimedia :: Sound/Audio
Requires-Python: >=3.0
License-File: LICENSE
Requires-Dist: python-vlc
